<?xml version="1.0" encoding="utf-8" ?>
<dwsync>
<file name="ae.svg" server="trausox.com/public_html/tkonect/" local="132784235330000000" remote="132804177600000000" Dst="0" />
<file name="ad.svg" server="trausox.com/public_html/tkonect/" local="132784235330000000" remote="132804177600000000" Dst="0" />
<file name="af.svg" server="trausox.com/public_html/tkonect/" local="132784235330000000" remote="132804177600000000" Dst="0" />
<file name="ag.svg" server="trausox.com/public_html/tkonect/" local="132784235330000000" remote="132804177600000000" Dst="0" />
<file name="ai.svg" server="trausox.com/public_html/tkonect/" local="132784235330000000" remote="132804177600000000" Dst="0" />
<file name="al.svg" server="trausox.com/public_html/tkonect/" local="132784235330000000" remote="132804177600000000" Dst="0" />
<file name="am.svg" server="trausox.com/public_html/tkonect/" local="132784235330000000" remote="132804177600000000" Dst="0" />
<file name="ao.svg" server="trausox.com/public_html/tkonect/" local="132784235330000000" remote="132804177600000000" Dst="0" />
<file name="aq.svg" server="trausox.com/public_html/tkonect/" local="132784235330000000" remote="132804177600000000" Dst="0" />
<file name="ar.svg" server="trausox.com/public_html/tkonect/" local="132784235330000000" remote="132804177600000000" Dst="0" />
<file name="as.svg" server="trausox.com/public_html/tkonect/" local="132784235330000000" remote="132804177600000000" Dst="0" />
<file name="at.svg" server="trausox.com/public_html/tkonect/" local="132784235330000000" remote="132804177600000000" Dst="0" />
<file name="au.svg" server="trausox.com/public_html/tkonect/" local="132784235330000000" remote="132804177600000000" Dst="0" />
<file name="aw.svg" server="trausox.com/public_html/tkonect/" local="132784235330000000" remote="132804177600000000" Dst="0" />
<file name="ax.svg" server="trausox.com/public_html/tkonect/" local="132784235330000000" remote="132804177600000000" Dst="0" />
<file name="az.svg" server="trausox.com/public_html/tkonect/" local="132784235330000000" remote="132804178200000000" Dst="0" />
<file name="ba.svg" server="trausox.com/public_html/tkonect/" local="132784235330000000" remote="132804178200000000" Dst="0" />
<file name="bb.svg" server="trausox.com/public_html/tkonect/" local="132784235330000000" remote="132804178200000000" Dst="0" />
<file name="be.svg" server="trausox.com/public_html/tkonect/" local="132784235330000000" remote="132804178200000000" Dst="0" />
<file name="bd.svg" server="trausox.com/public_html/tkonect/" local="132784235330000000" remote="132804178200000000" Dst="0" />
<file name="bf.svg" server="trausox.com/public_html/tkonect/" local="132784235330000000" remote="132804178200000000" Dst="0" />
<file name="bh.svg" server="trausox.com/public_html/tkonect/" local="132784235330000000" remote="132804178200000000" Dst="0" />
<file name="bg.svg" server="trausox.com/public_html/tkonect/" local="132784235330000000" remote="132804178200000000" Dst="0" />
<file name="bi.svg" server="trausox.com/public_html/tkonect/" local="132784235330000000" remote="132804178200000000" Dst="0" />
<file name="bj.svg" server="trausox.com/public_html/tkonect/" local="132784235330000000" remote="132804178200000000" Dst="0" />
<file name="bl.svg" server="trausox.com/public_html/tkonect/" local="132784235330000000" remote="132804178200000000" Dst="0" />
<file name="bm.svg" server="trausox.com/public_html/tkonect/" local="132784235330000000" remote="132804178200000000" Dst="0" />
<file name="bn.svg" server="trausox.com/public_html/tkonect/" local="132784235330000000" remote="132804178200000000" Dst="0" />
<file name="bq.svg" server="trausox.com/public_html/tkonect/" local="132784235330000000" remote="132804178200000000" Dst="0" />
<file name="bo.svg" server="trausox.com/public_html/tkonect/" local="132784235330000000" remote="132804178200000000" Dst="0" />
<file name="br.svg" server="trausox.com/public_html/tkonect/" local="132784235330000000" remote="132804178200000000" Dst="0" />
<file name="bs.svg" server="trausox.com/public_html/tkonect/" local="132784235330000000" remote="132804178200000000" Dst="0" />
<file name="bt.svg" server="trausox.com/public_html/tkonect/" local="132784235330000000" remote="132804178200000000" Dst="0" />
<file name="bv.svg" server="trausox.com/public_html/tkonect/" local="132784235330000000" remote="132804178200000000" Dst="0" />
<file name="bw.svg" server="trausox.com/public_html/tkonect/" local="132784235330000000" remote="132804178200000000" Dst="0" />
<file name="by.svg" server="trausox.com/public_html/tkonect/" local="132784235330000000" remote="132804178200000000" Dst="0" />
<file name="ca.svg" server="trausox.com/public_html/tkonect/" local="132784235330000000" remote="132804178200000000" Dst="0" />
<file name="bz.svg" server="trausox.com/public_html/tkonect/" local="132784235330000000" remote="132804178200000000" Dst="0" />
<file name="cc.svg" server="trausox.com/public_html/tkonect/" local="132784235330000000" remote="132804178200000000" Dst="0" />
<file name="cd.svg" server="trausox.com/public_html/tkonect/" local="132784235330000000" remote="132804178200000000" Dst="0" />
<file name="cf.svg" server="trausox.com/public_html/tkonect/" local="132784235330000000" remote="132804178200000000" Dst="0" />
<file name="cg.svg" server="trausox.com/public_html/tkonect/" local="132784235330000000" remote="132804178200000000" Dst="0" />
<file name="ch.svg" server="trausox.com/public_html/tkonect/" local="132784235330000000" remote="132804178200000000" Dst="0" />
<file name="ci.svg" server="trausox.com/public_html/tkonect/" local="132784235330000000" remote="132804178200000000" Dst="0" />
<file name="ck.svg" server="trausox.com/public_html/tkonect/" local="132784235330000000" remote="132804178200000000" Dst="0" />
<file name="cl.svg" server="trausox.com/public_html/tkonect/" local="132784235330000000" remote="132804178200000000" Dst="0" />
<file name="cm.svg" server="trausox.com/public_html/tkonect/" local="132784235330000000" remote="132804178200000000" Dst="0" />
<file name="cn.svg" server="trausox.com/public_html/tkonect/" local="132784235330000000" remote="132804178200000000" Dst="0" />
<file name="co.svg" server="trausox.com/public_html/tkonect/" local="132784235330000000" remote="132804178200000000" Dst="0" />
<file name="cr.svg" server="trausox.com/public_html/tkonect/" local="132784235330000000" remote="132804178200000000" Dst="0" />
<file name="cv.svg" server="trausox.com/public_html/tkonect/" local="132784235330000000" remote="132804178200000000" Dst="0" />
<file name="cu.svg" server="trausox.com/public_html/tkonect/" local="132784235330000000" remote="132804178200000000" Dst="0" />
<file name="cw.svg" server="trausox.com/public_html/tkonect/" local="132784235330000000" remote="132804178200000000" Dst="0" />
<file name="cy.svg" server="trausox.com/public_html/tkonect/" local="132784235330000000" remote="132804178200000000" Dst="0" />
<file name="cx.svg" server="trausox.com/public_html/tkonect/" local="132784235330000000" remote="132804178200000000" Dst="0" />
<file name="cz.svg" server="trausox.com/public_html/tkonect/" local="132784235330000000" remote="132804178200000000" Dst="0" />
<file name="de.svg" server="trausox.com/public_html/tkonect/" local="132784235330000000" remote="132804178200000000" Dst="0" />
<file name="dj.svg" server="trausox.com/public_html/tkonect/" local="132784235330000000" remote="132804178200000000" Dst="0" />
<file name="dk.svg" server="trausox.com/public_html/tkonect/" local="132784235330000000" remote="132804178200000000" Dst="0" />
<file name="dm.svg" server="trausox.com/public_html/tkonect/" local="132784235330000000" remote="132804178200000000" Dst="0" />
<file name="dz.svg" server="trausox.com/public_html/tkonect/" local="132784235330000000" remote="132804178200000000" Dst="0" />
<file name="ec.svg" server="trausox.com/public_html/tkonect/" local="132784235330000000" remote="132804178200000000" Dst="0" />
<file name="ee.svg" server="trausox.com/public_html/tkonect/" local="132784235330000000" remote="132804178200000000" Dst="0" />
<file name="eg.svg" server="trausox.com/public_html/tkonect/" local="132784235330000000" remote="132804178200000000" Dst="0" />
<file name="do.svg" server="trausox.com/public_html/tkonect/" local="132784235330000000" remote="132804178200000000" Dst="0" />
<file name="eh.svg" server="trausox.com/public_html/tkonect/" local="132784235330000000" remote="132804178200000000" Dst="0" />
<file name="er.svg" server="trausox.com/public_html/tkonect/" local="132784235330000000" remote="132804178200000000" Dst="0" />
<file name="es-ca.svg" server="trausox.com/public_html/tkonect/" local="132784235330000000" remote="132804178200000000" Dst="0" />
<file name="es-ga.svg" server="trausox.com/public_html/tkonect/" local="132784235330000000" remote="132804178200000000" Dst="0" />
<file name="et.svg" server="trausox.com/public_html/tkonect/" local="132784235330000000" remote="132804178200000000" Dst="0" />
<file name="eu.svg" server="trausox.com/public_html/tkonect/" local="132784235330000000" remote="132804178200000000" Dst="0" />
<file name="es.svg" server="trausox.com/public_html/tkonect/" local="132784235330000000" remote="132804178200000000" Dst="0" />
<file name="fi.svg" server="trausox.com/public_html/tkonect/" local="132784235330000000" remote="132804178200000000" Dst="0" />
<file name="fj.svg" server="trausox.com/public_html/tkonect/" local="132784235330000000" remote="132804178200000000" Dst="0" />
<file name="fk.svg" server="trausox.com/public_html/tkonect/" local="132784235330000000" remote="132804178200000000" Dst="0" />
<file name="fo.svg" server="trausox.com/public_html/tkonect/" local="132784235330000000" remote="132804178200000000" Dst="0" />
<file name="fm.svg" server="trausox.com/public_html/tkonect/" local="132784235330000000" remote="132804178200000000" Dst="0" />
<file name="fr.svg" server="trausox.com/public_html/tkonect/" local="132784235330000000" remote="132804178200000000" Dst="0" />
<file name="ga.svg" server="trausox.com/public_html/tkonect/" local="132784235330000000" remote="132804178200000000" Dst="0" />
<file name="gb-eng.svg" server="trausox.com/public_html/tkonect/" local="132784235330000000" remote="132804178200000000" Dst="0" />
<file name="gb-nir.svg" server="trausox.com/public_html/tkonect/" local="132784235330000000" remote="132804178200000000" Dst="0" />
<file name="gb-sct.svg" server="trausox.com/public_html/tkonect/" local="132784235330000000" remote="132804178200000000" Dst="0" />
<file name="gb-wls.svg" server="trausox.com/public_html/tkonect/" local="132784235330000000" remote="132804178200000000" Dst="0" />
<file name="gb.svg" server="trausox.com/public_html/tkonect/" local="132784235330000000" remote="132804178200000000" Dst="0" />
<file name="gd.svg" server="trausox.com/public_html/tkonect/" local="132784235330000000" remote="132804178200000000" Dst="0" />
<file name="ge.svg" server="trausox.com/public_html/tkonect/" local="132784235330000000" remote="132804178200000000" Dst="0" />
<file name="gf.svg" server="trausox.com/public_html/tkonect/" local="132784235330000000" remote="132804178200000000" Dst="0" />
<file name="gh.svg" server="trausox.com/public_html/tkonect/" local="132784235330000000" remote="132804178200000000" Dst="0" />
<file name="gg.svg" server="trausox.com/public_html/tkonect/" local="132784235330000000" remote="132804178200000000" Dst="0" />
<file name="gi.svg" server="trausox.com/public_html/tkonect/" local="132784235330000000" remote="132804178200000000" Dst="0" />
<file name="gl.svg" server="trausox.com/public_html/tkonect/" local="132784235330000000" remote="132804178200000000" Dst="0" />
<file name="gm.svg" server="trausox.com/public_html/tkonect/" local="132784235330000000" remote="132804178200000000" Dst="0" />
<file name="gn.svg" server="trausox.com/public_html/tkonect/" local="132784235330000000" remote="132804178200000000" Dst="0" />
<file name="gp.svg" server="trausox.com/public_html/tkonect/" local="132784235330000000" remote="132804178200000000" Dst="0" />
<file name="gq.svg" server="trausox.com/public_html/tkonect/" local="132784235330000000" remote="132804178200000000" Dst="0" />
<file name="gr.svg" server="trausox.com/public_html/tkonect/" local="132784235330000000" remote="132804178200000000" Dst="0" />
<file name="gs.svg" server="trausox.com/public_html/tkonect/" local="132784235330000000" remote="132804178200000000" Dst="0" />
<file name="gt.svg" server="trausox.com/public_html/tkonect/" local="132784235330000000" remote="132804178200000000" Dst="0" />
<file name="gw.svg" server="trausox.com/public_html/tkonect/" local="132784235330000000" remote="132804178200000000" Dst="0" />
<file name="gu.svg" server="trausox.com/public_html/tkonect/" local="132784235330000000" remote="132804178200000000" Dst="0" />
<file name="gy.svg" server="trausox.com/public_html/tkonect/" local="132784235330000000" remote="132804178200000000" Dst="0" />
<file name="hk.svg" server="trausox.com/public_html/tkonect/" local="132784235330000000" remote="132804178200000000" Dst="0" />
<file name="hm.svg" server="trausox.com/public_html/tkonect/" local="132784235330000000" remote="132804178200000000" Dst="0" />
<file name="hn.svg" server="trausox.com/public_html/tkonect/" local="132784235330000000" remote="132804178200000000" Dst="0" />
<file name="hr.svg" server="trausox.com/public_html/tkonect/" local="132784235330000000" remote="132804178200000000" Dst="0" />
<file name="ht.svg" server="trausox.com/public_html/tkonect/" local="132784235330000000" remote="132804178200000000" Dst="0" />
<file name="hu.svg" server="trausox.com/public_html/tkonect/" local="132784235330000000" remote="132804178200000000" Dst="0" />
<file name="id.svg" server="trausox.com/public_html/tkonect/" local="132784235330000000" remote="132804178200000000" Dst="0" />
<file name="ie.svg" server="trausox.com/public_html/tkonect/" local="132784235330000000" remote="132804178200000000" Dst="0" />
<file name="il.svg" server="trausox.com/public_html/tkonect/" local="132784235330000000" remote="132804178200000000" Dst="0" />
<file name="im.svg" server="trausox.com/public_html/tkonect/" local="132784235330000000" remote="132804178200000000" Dst="0" />
<file name="in.svg" server="trausox.com/public_html/tkonect/" local="132784235330000000" remote="132804178200000000" Dst="0" />
<file name="io.svg" server="trausox.com/public_html/tkonect/" local="132784235330000000" remote="132804178200000000" Dst="0" />
<file name="iq.svg" server="trausox.com/public_html/tkonect/" local="132784235330000000" remote="132804178200000000" Dst="0" />
<file name="ir.svg" server="trausox.com/public_html/tkonect/" local="132784235330000000" remote="132804178200000000" Dst="0" />
<file name="is.svg" server="trausox.com/public_html/tkonect/" local="132784235330000000" remote="132804178200000000" Dst="0" />
<file name="it.svg" server="trausox.com/public_html/tkonect/" local="132784235330000000" remote="132804178200000000" Dst="0" />
<file name="je.svg" server="trausox.com/public_html/tkonect/" local="132784235330000000" remote="132804178200000000" Dst="0" />
<file name="jm.svg" server="trausox.com/public_html/tkonect/" local="132784235330000000" remote="132804178200000000" Dst="0" />
<file name="jo.svg" server="trausox.com/public_html/tkonect/" local="132784235330000000" remote="132804178200000000" Dst="0" />
<file name="jp.svg" server="trausox.com/public_html/tkonect/" local="132784235330000000" remote="132804178200000000" Dst="0" />
<file name="ke.svg" server="trausox.com/public_html/tkonect/" local="132784235330000000" remote="132804178200000000" Dst="0" />
<file name="kg.svg" server="trausox.com/public_html/tkonect/" local="132784235330000000" remote="132804178200000000" Dst="0" />
<file name="kh.svg" server="trausox.com/public_html/tkonect/" local="132784235330000000" remote="132804178200000000" Dst="0" />
<file name="ki.svg" server="trausox.com/public_html/tkonect/" local="132784235330000000" remote="132804178200000000" Dst="0" />
<file name="km.svg" server="trausox.com/public_html/tkonect/" local="132784235330000000" remote="132804178200000000" Dst="0" />
<file name="kn.svg" server="trausox.com/public_html/tkonect/" local="132784235330000000" remote="132804178200000000" Dst="0" />
<file name="kp.svg" server="trausox.com/public_html/tkonect/" local="132784235330000000" remote="132804178200000000" Dst="0" />
<file name="kr.svg" server="trausox.com/public_html/tkonect/" local="132784235330000000" remote="132804178200000000" Dst="0" />
<file name="kw.svg" server="trausox.com/public_html/tkonect/" local="132784235330000000" remote="132804178200000000" Dst="0" />
<file name="ky.svg" server="trausox.com/public_html/tkonect/" local="132784235330000000" remote="132804178200000000" Dst="0" />
<file name="kz.svg" server="trausox.com/public_html/tkonect/" local="132784235330000000" remote="132804178200000000" Dst="0" />
<file name="la.svg" server="trausox.com/public_html/tkonect/" local="132784235330000000" remote="132804178200000000" Dst="0" />
<file name="lb.svg" server="trausox.com/public_html/tkonect/" local="132784235330000000" remote="132804178200000000" Dst="0" />
<file name="lc.svg" server="trausox.com/public_html/tkonect/" local="132784235330000000" remote="132804178200000000" Dst="0" />
<file name="li.svg" server="trausox.com/public_html/tkonect/" local="132784235330000000" remote="132804178200000000" Dst="0" />
<file name="lk.svg" server="trausox.com/public_html/tkonect/" local="132784235330000000" remote="132804178200000000" Dst="0" />
<file name="ls.svg" server="trausox.com/public_html/tkonect/" local="132784235330000000" remote="132804178200000000" Dst="0" />
<file name="lr.svg" server="trausox.com/public_html/tkonect/" local="132784235330000000" remote="132804178200000000" Dst="0" />
<file name="lt.svg" server="trausox.com/public_html/tkonect/" local="132784235330000000" remote="132804178200000000" Dst="0" />
<file name="lu.svg" server="trausox.com/public_html/tkonect/" local="132784235330000000" remote="132804178200000000" Dst="0" />
<file name="lv.svg" server="trausox.com/public_html/tkonect/" local="132784235330000000" remote="132804178200000000" Dst="0" />
<file name="ly.svg" server="trausox.com/public_html/tkonect/" local="132784235330000000" remote="132804178200000000" Dst="0" />
<file name="ma.svg" server="trausox.com/public_html/tkonect/" local="132784235330000000" remote="132804178200000000" Dst="0" />
<file name="mc.svg" server="trausox.com/public_html/tkonect/" local="132784235330000000" remote="132804178200000000" Dst="0" />
<file name="md.svg" server="trausox.com/public_html/tkonect/" local="132784235330000000" remote="132804178800000000" Dst="0" />
<file name="me.svg" server="trausox.com/public_html/tkonect/" local="132784235330000000" remote="132804178800000000" Dst="0" />
<file name="mf.svg" server="trausox.com/public_html/tkonect/" local="132784235330000000" remote="132804178800000000" Dst="0" />
<file name="mg.svg" server="trausox.com/public_html/tkonect/" local="132784235330000000" remote="132804178800000000" Dst="0" />
<file name="mh.svg" server="trausox.com/public_html/tkonect/" local="132784235330000000" remote="132804178800000000" Dst="0" />
<file name="mk.svg" server="trausox.com/public_html/tkonect/" local="132784235330000000" remote="132804178800000000" Dst="0" />
<file name="ml.svg" server="trausox.com/public_html/tkonect/" local="132784235330000000" remote="132804178800000000" Dst="0" />
<file name="mm.svg" server="trausox.com/public_html/tkonect/" local="132784235330000000" remote="132804178800000000" Dst="0" />
<file name="mn.svg" server="trausox.com/public_html/tkonect/" local="132784235330000000" remote="132804178800000000" Dst="0" />
<file name="mo.svg" server="trausox.com/public_html/tkonect/" local="132784235330000000" remote="132804178800000000" Dst="0" />
<file name="mq.svg" server="trausox.com/public_html/tkonect/" local="132784235330000000" remote="132804178800000000" Dst="0" />
<file name="mp.svg" server="trausox.com/public_html/tkonect/" local="132784235330000000" remote="132804178800000000" Dst="0" />
<file name="mr.svg" server="trausox.com/public_html/tkonect/" local="132784235330000000" remote="132804178800000000" Dst="0" />
<file name="ms.svg" server="trausox.com/public_html/tkonect/" local="132784235330000000" remote="132804178800000000" Dst="0" />
<file name="mt.svg" server="trausox.com/public_html/tkonect/" local="132784235330000000" remote="132804178800000000" Dst="0" />
<file name="mu.svg" server="trausox.com/public_html/tkonect/" local="132784235330000000" remote="132804178800000000" Dst="0" />
<file name="mv.svg" server="trausox.com/public_html/tkonect/" local="132784235330000000" remote="132804178800000000" Dst="0" />
<file name="mw.svg" server="trausox.com/public_html/tkonect/" local="132784235330000000" remote="132804178800000000" Dst="0" />
<file name="my.svg" server="trausox.com/public_html/tkonect/" local="132784235330000000" remote="132804178800000000" Dst="0" />
<file name="mx.svg" server="trausox.com/public_html/tkonect/" local="132784235330000000" remote="132804178800000000" Dst="0" />
<file name="mz.svg" server="trausox.com/public_html/tkonect/" local="132784235330000000" remote="132804178800000000" Dst="0" />
<file name="na.svg" server="trausox.com/public_html/tkonect/" local="132784235330000000" remote="132804178800000000" Dst="0" />
<file name="nc.svg" server="trausox.com/public_html/tkonect/" local="132784235330000000" remote="132804178800000000" Dst="0" />
<file name="ne.svg" server="trausox.com/public_html/tkonect/" local="132784235330000000" remote="132804178800000000" Dst="0" />
<file name="nf.svg" server="trausox.com/public_html/tkonect/" local="132784235330000000" remote="132804178800000000" Dst="0" />
<file name="ng.svg" server="trausox.com/public_html/tkonect/" local="132784235330000000" remote="132804178800000000" Dst="0" />
<file name="ni.svg" server="trausox.com/public_html/tkonect/" local="132784235330000000" remote="132804178800000000" Dst="0" />
<file name="nl.svg" server="trausox.com/public_html/tkonect/" local="132784235330000000" remote="132804178800000000" Dst="0" />
<file name="no.svg" server="trausox.com/public_html/tkonect/" local="132784235330000000" remote="132804178800000000" Dst="0" />
<file name="np.svg" server="trausox.com/public_html/tkonect/" local="132784235330000000" remote="132804178800000000" Dst="0" />
<file name="nu.svg" server="trausox.com/public_html/tkonect/" local="132784235330000000" remote="132804178800000000" Dst="0" />
<file name="nr.svg" server="trausox.com/public_html/tkonect/" local="132784235330000000" remote="132804178800000000" Dst="0" />
<file name="nz.svg" server="trausox.com/public_html/tkonect/" local="132784235330000000" remote="132804178800000000" Dst="0" />
<file name="om.svg" server="trausox.com/public_html/tkonect/" local="132784235330000000" remote="132804178800000000" Dst="0" />
<file name="pa.svg" server="trausox.com/public_html/tkonect/" local="132784235330000000" remote="132804178800000000" Dst="0" />
<file name="pf.svg" server="trausox.com/public_html/tkonect/" local="132784235330000000" remote="132804178800000000" Dst="0" />
<file name="pg.svg" server="trausox.com/public_html/tkonect/" local="132784235330000000" remote="132804178800000000" Dst="0" />
<file name="pe.svg" server="trausox.com/public_html/tkonect/" local="132784235330000000" remote="132804178800000000" Dst="0" />
<file name="ph.svg" server="trausox.com/public_html/tkonect/" local="132784235330000000" remote="132804178800000000" Dst="0" />
<file name="pk.svg" server="trausox.com/public_html/tkonect/" local="132784235330000000" remote="132804178800000000" Dst="0" />
<file name="pl.svg" server="trausox.com/public_html/tkonect/" local="132784235330000000" remote="132804178800000000" Dst="0" />
<file name="pm.svg" server="trausox.com/public_html/tkonect/" local="132784235330000000" remote="132804178800000000" Dst="0" />
<file name="pn.svg" server="trausox.com/public_html/tkonect/" local="132784235330000000" remote="132804178800000000" Dst="0" />
<file name="pr.svg" server="trausox.com/public_html/tkonect/" local="132784235330000000" remote="132804178800000000" Dst="0" />
<file name="pt.svg" server="trausox.com/public_html/tkonect/" local="132784235330000000" remote="132804178800000000" Dst="0" />
<file name="ps.svg" server="trausox.com/public_html/tkonect/" local="132784235330000000" remote="132804178800000000" Dst="0" />
<file name="pw.svg" server="trausox.com/public_html/tkonect/" local="132784235330000000" remote="132804178800000000" Dst="0" />
<file name="py.svg" server="trausox.com/public_html/tkonect/" local="132784235330000000" remote="132804178800000000" Dst="0" />
<file name="qa.svg" server="trausox.com/public_html/tkonect/" local="132784235330000000" remote="132804178800000000" Dst="0" />
<file name="re.svg" server="trausox.com/public_html/tkonect/" local="132784235330000000" remote="132804178800000000" Dst="0" />
<file name="ro.svg" server="trausox.com/public_html/tkonect/" local="132784235330000000" remote="132804178800000000" Dst="0" />
<file name="ru.svg" server="trausox.com/public_html/tkonect/" local="132784235330000000" remote="132804178800000000" Dst="0" />
<file name="rw.svg" server="trausox.com/public_html/tkonect/" local="132784235330000000" remote="132804178800000000" Dst="0" />
<file name="rs.svg" server="trausox.com/public_html/tkonect/" local="132784235330000000" remote="132804178800000000" Dst="0" />
<file name="sa.svg" server="trausox.com/public_html/tkonect/" local="132784235330000000" remote="132804178800000000" Dst="0" />
<file name="sc.svg" server="trausox.com/public_html/tkonect/" local="132784235330000000" remote="132804178800000000" Dst="0" />
<file name="sb.svg" server="trausox.com/public_html/tkonect/" local="132784235330000000" remote="132804178800000000" Dst="0" />
<file name="sd.svg" server="trausox.com/public_html/tkonect/" local="132784235330000000" remote="132804178800000000" Dst="0" />
<file name="se.svg" server="trausox.com/public_html/tkonect/" local="132784235330000000" remote="132804178800000000" Dst="0" />
<file name="sg.svg" server="trausox.com/public_html/tkonect/" local="132784235330000000" remote="132804178800000000" Dst="0" />
<file name="sh.svg" server="trausox.com/public_html/tkonect/" local="132784235330000000" remote="132804178800000000" Dst="0" />
<file name="si.svg" server="trausox.com/public_html/tkonect/" local="132784235330000000" remote="132804178800000000" Dst="0" />
<file name="sj.svg" server="trausox.com/public_html/tkonect/" local="132784235330000000" remote="132804178800000000" Dst="0" />
<file name="sk.svg" server="trausox.com/public_html/tkonect/" local="132784235330000000" remote="132804178800000000" Dst="0" />
<file name="sl.svg" server="trausox.com/public_html/tkonect/" local="132784235330000000" remote="132804178800000000" Dst="0" />
<file name="sn.svg" server="trausox.com/public_html/tkonect/" local="132784235330000000" remote="132804178800000000" Dst="0" />
<file name="so.svg" server="trausox.com/public_html/tkonect/" local="132784235330000000" remote="132804178800000000" Dst="0" />
<file name="sm.svg" server="trausox.com/public_html/tkonect/" local="132784235330000000" remote="132804178800000000" Dst="0" />
<file name="ss.svg" server="trausox.com/public_html/tkonect/" local="132784235330000000" remote="132804178800000000" Dst="0" />
<file name="sr.svg" server="trausox.com/public_html/tkonect/" local="132784235330000000" remote="132804178800000000" Dst="0" />
<file name="st.svg" server="trausox.com/public_html/tkonect/" local="132784235330000000" remote="132804178800000000" Dst="0" />
<file name="sx.svg" server="trausox.com/public_html/tkonect/" local="132784235330000000" remote="132804178800000000" Dst="0" />
<file name="sy.svg" server="trausox.com/public_html/tkonect/" local="132784235330000000" remote="132804178800000000" Dst="0" />
<file name="sv.svg" server="trausox.com/public_html/tkonect/" local="132784235330000000" remote="132804178800000000" Dst="0" />
<file name="sz.svg" server="trausox.com/public_html/tkonect/" local="132784235330000000" remote="132804178800000000" Dst="0" />
<file name="tc.svg" server="trausox.com/public_html/tkonect/" local="132784235330000000" remote="132804178800000000" Dst="0" />
<file name="td.svg" server="trausox.com/public_html/tkonect/" local="132784235330000000" remote="132804178800000000" Dst="0" />
<file name="tf.svg" server="trausox.com/public_html/tkonect/" local="132784235330000000" remote="132804178800000000" Dst="0" />
<file name="tg.svg" server="trausox.com/public_html/tkonect/" local="132784235330000000" remote="132804178800000000" Dst="0" />
<file name="th.svg" server="trausox.com/public_html/tkonect/" local="132784235330000000" remote="132804178800000000" Dst="0" />
<file name="tj.svg" server="trausox.com/public_html/tkonect/" local="132784235330000000" remote="132804178800000000" Dst="0" />
<file name="tk.svg" server="trausox.com/public_html/tkonect/" local="132784235330000000" remote="132804178800000000" Dst="0" />
<file name="tl.svg" server="trausox.com/public_html/tkonect/" local="132784235330000000" remote="132804178800000000" Dst="0" />
<file name="tm.svg" server="trausox.com/public_html/tkonect/" local="132784235330000000" remote="132804178800000000" Dst="0" />
<file name="tn.svg" server="trausox.com/public_html/tkonect/" local="132784235330000000" remote="132804178800000000" Dst="0" />
<file name="tr.svg" server="trausox.com/public_html/tkonect/" local="132784235330000000" remote="132804178800000000" Dst="0" />
<file name="to.svg" server="trausox.com/public_html/tkonect/" local="132784235330000000" remote="132804178800000000" Dst="0" />
<file name="tt.svg" server="trausox.com/public_html/tkonect/" local="132784235330000000" remote="132804178800000000" Dst="0" />
<file name="tv.svg" server="trausox.com/public_html/tkonect/" local="132784235330000000" remote="132804178800000000" Dst="0" />
<file name="tw.svg" server="trausox.com/public_html/tkonect/" local="132784235330000000" remote="132804178800000000" Dst="0" />
<file name="tz.svg" server="trausox.com/public_html/tkonect/" local="132784235330000000" remote="132804178800000000" Dst="0" />
<file name="ua.svg" server="trausox.com/public_html/tkonect/" local="132784235330000000" remote="132804178800000000" Dst="0" />
<file name="ug.svg" server="trausox.com/public_html/tkonect/" local="132784235330000000" remote="132804178800000000" Dst="0" />
<file name="um.svg" server="trausox.com/public_html/tkonect/" local="132784235330000000" remote="132804178800000000" Dst="0" />
<file name="un.svg" server="trausox.com/public_html/tkonect/" local="132784235330000000" remote="132804178800000000" Dst="0" />
<file name="us.svg" server="trausox.com/public_html/tkonect/" local="132784235330000000" remote="132804178800000000" Dst="0" />
<file name="uy.svg" server="trausox.com/public_html/tkonect/" local="132784235330000000" remote="132804178800000000" Dst="0" />
<file name="uz.svg" server="trausox.com/public_html/tkonect/" local="132784235330000000" remote="132804178800000000" Dst="0" />
<file name="vc.svg" server="trausox.com/public_html/tkonect/" local="132784235330000000" remote="132804178800000000" Dst="0" />
<file name="va.svg" server="trausox.com/public_html/tkonect/" local="132784235330000000" remote="132804178800000000" Dst="0" />
<file name="ve.svg" server="trausox.com/public_html/tkonect/" local="132784235330000000" remote="132804178800000000" Dst="0" />
<file name="vg.svg" server="trausox.com/public_html/tkonect/" local="132784235330000000" remote="132804178800000000" Dst="0" />
<file name="vi.svg" server="trausox.com/public_html/tkonect/" local="132784235330000000" remote="132804178800000000" Dst="0" />
<file name="vn.svg" server="trausox.com/public_html/tkonect/" local="132784235330000000" remote="132804178800000000" Dst="0" />
<file name="vu.svg" server="trausox.com/public_html/tkonect/" local="132784235330000000" remote="132804178800000000" Dst="0" />
<file name="wf.svg" server="trausox.com/public_html/tkonect/" local="132784235330000000" remote="132804178800000000" Dst="0" />
<file name="ws.svg" server="trausox.com/public_html/tkonect/" local="132784235330000000" remote="132804178800000000" Dst="0" />
<file name="xk.svg" server="trausox.com/public_html/tkonect/" local="132784235330000000" remote="132804178800000000" Dst="0" />
<file name="ye.svg" server="trausox.com/public_html/tkonect/" local="132784235330000000" remote="132804178800000000" Dst="0" />
<file name="yt.svg" server="trausox.com/public_html/tkonect/" local="132784235330000000" remote="132804178800000000" Dst="0" />
<file name="za.svg" server="trausox.com/public_html/tkonect/" local="132784235330000000" remote="132804178800000000" Dst="0" />
<file name="zm.svg" server="trausox.com/public_html/tkonect/" local="132784235330000000" remote="132804178800000000" Dst="0" />
<file name="zw.svg" server="trausox.com/public_html/tkonect/" local="132784235330000000" remote="132804178800000000" Dst="0" />
</dwsync>